{
  "2025-11-11": [
    {
      "room": "301",
      "time": "23:46:15"
    },
    {
      "room": "504",
      "time": "00:07:05"
    },
    {
      "room": "503",
      "time": "00:07:11"
    },
    {
      "room": "502",
      "time": "00:07:17"
    },
    {
      "room": "202",
      "time": "00:08:20"
    },
    {
      "room": "106",
      "time": "00:08:29"
    },
    {
      "room": "105",
      "time": "00:08:32"
    },
    {
      "room": "001",
      "time": "00:08:47"
    },
    {
      "room": "104",
      "time": "00:13:42"
    },
    {
      "room": "101",
      "time": "00:17:39"
    },
    {
      "room": "103",
      "time": "00:18:01"
    },
    {
      "room": "402",
      "time": "00:27:37"
    },
    {
      "room": "405",
      "time": "00:30:03"
    },
    {
      "room": "304",
      "time": "00:32:12"
    },
    {
      "room": "306",
      "time": "00:34:00"
    },
    {
      "room": "206",
      "time": "00:58:50"
    },
    {
      "room": "302",
      "time": "01:17:02"
    }
  ]
}